d20/__init__.py
d20/__main__.py
d20/dice.py
d20/diceast.py
d20/errors.py
d20/expression.py
d20/grammar.lark
d20/stringifiers.py
d20/utils.py
d20-1.1.2.dist-info/LICENSE
d20-1.1.2.dist-info/METADATA
d20-1.1.2.dist-info/WHEEL
d20-1.1.2.dist-info/top_level.txt
d20-1.1.2.dist-info/RECORD
