Metadata-Version: 2.1
Name: d20
Version: 1.1.2
Summary: A formal grammar-based dice parser and roller for D&D and other dice systems.
Home-page: https://github.com/avrae/formaldice
Author: Andrew Zhu
Author-email: andrew@zhu.codes
License: UNKNOWN
Platform: UNKNOWN
Classifier: Programming Language :: Python :: 3
Classifier: Programming Language :: Python :: 3.6
Classifier: Programming Language :: Python :: 3.7
Classifier: Programming Language :: Python :: 3.8
Classifier: License :: OSI Approved :: MIT License
Classifier: Operating System :: OS Independent
Classifier: Topic :: Games/Entertainment :: Board Games
Classifier: Topic :: Games/Entertainment :: Role-Playing
Requires-Python: >=3.6
